ccard/__init__.py
ccard/americanexpress
ccard/discover
ccard/main.py
ccard/mastercard
ccard/visa
ccard-0.2.0.dist-info/AUTHORS.rst
ccard-0.2.0.dist-info/LICENSE.txt
ccard-0.2.0.dist-info/METADATA
ccard-0.2.0.dist-info/WHEEL
ccard-0.2.0.dist-info/entry_points.txt
ccard-0.2.0.dist-info/top_level.txt
ccard-0.2.0.dist-info/RECORD
