Metadata-Version: 2.1
Name: ccard
Version: 0.2.0
Summary: credit card generator
Home-page: https://github.com/davidsamir/credit-card-generator/
Author: David Samir
Author-email: dsamir@davidsamir.com
License: MIT
Classifier: Development Status :: 4 - Beta
Classifier: Environment :: Console
Classifier: License :: OSI Approved :: MIT License
Classifier: Operating System :: OS Independent
Classifier: Programming Language :: Python
Classifier: Programming Language :: Python :: 2.7
Classifier: Programming Language :: Python :: 3
Classifier: Programming Language :: Python :: 3.2
Classifier: Programming Language :: Python :: 3.3
Classifier: Programming Language :: Python :: 3.4
Classifier: Programming Language :: Python :: Implementation :: PyPy
License-File: LICENSE.txt
License-File: AUTHORS.rst
